wrk_platform_sdk/__init__.py
wrk_platform_sdk/api_client.py
wrk_platform_sdk/api_response.py
wrk_platform_sdk/configuration.py
wrk_platform_sdk/exceptions.py
wrk_platform_sdk/py.typed
wrk_platform_sdk/rest.py
wrk_platform_sdk/api/__init__.py
wrk_platform_sdk/api/connected_accounts_api.py
wrk_platform_sdk/api/launch_activities_api.py
wrk_platform_sdk/api/launches_api.py
wrk_platform_sdk/api/media_library_api.py
wrk_platform_sdk/api/webhooks_api.py
wrk_platform_sdk/api/wrk_action_resources_api.py
wrk_platform_sdk/api/wrkflows_api.py
wrk_platform_sdk/models/__init__.py
wrk_platform_sdk/models/action_application.py
wrk_platform_sdk/models/action_application_spec.py
wrk_platform_sdk/models/connected_account.py
wrk_platform_sdk/models/create_connected_account_accepted_response.py
wrk_platform_sdk/models/create_connected_account_created_response.py
wrk_platform_sdk/models/create_connected_account_request.py
wrk_platform_sdk/models/create_media_library_file202_response.py
wrk_platform_sdk/models/create_media_library_file_request.py
wrk_platform_sdk/models/create_wrkflow_response.py
wrk_platform_sdk/models/credential.py
wrk_platform_sdk/models/credential_spec.py
wrk_platform_sdk/models/delete_media_library_file200_response.py
wrk_platform_sdk/models/get_action_applications_response.py
wrk_platform_sdk/models/get_connected_account_response.py
wrk_platform_sdk/models/get_connected_accounts_response.py
wrk_platform_sdk/models/get_credentials_response.py
wrk_platform_sdk/models/get_launch_activities_response.py
wrk_platform_sdk/models/get_launch_by_id_response.py
wrk_platform_sdk/models/get_launches_response.py
wrk_platform_sdk/models/get_media_library_file_by_id200_response.py
wrk_platform_sdk/models/get_media_library_files200_response.py
wrk_platform_sdk/models/get_outcomes_response.py
wrk_platform_sdk/models/get_wrk_actions_response.py
wrk_platform_sdk/models/get_wrkflow_by_uuid_response.py
wrk_platform_sdk/models/get_wrkflows_response.py
wrk_platform_sdk/models/launch.py
wrk_platform_sdk-3.4.0.dist-info/METADATA
wrk_platform_sdk-3.4.0.dist-info/WHEEL
wrk_platform_sdk-3.4.0.dist-info/top_level.txt
wrk_platform_sdk-3.4.0.dist-info/RECORD
