Metadata-Version: 2.4
Name: wrk_platform_sdk
Version: 3.4.0
Summary: Wrk Automation Platform - API v1
Home-page: 
Author: OpenAPI Generator community
Author-email: OpenAPI Generator Community <support@wrk.com>
Project-URL: Repository, https://github.com/GIT_USER_ID/GIT_REPO_ID
Keywords: OpenAPI,OpenAPI-Generator,Wrk Automation Platform - API v1
Requires-Python: >=3.9
Requires-Dist: urllib3<3.0.0,>=2.1.0
Requires-Dist: python-dateutil>=2.8.2
Requires-Dist: pydantic>=2
Requires-Dist: typing-extensions>=4.7.1
Requires-Dist: lazy-imports<2,>=1
Dynamic: author
